checkvsphere/__init__.py
checkvsphere/cli.py
checkvsphere/tools/__init__.py
checkvsphere/tools/cli.py
checkvsphere/tools/helper.py
checkvsphere/tools/pchelper.py
checkvsphere/tools/service_instance.py
checkvsphere/tools/serviceutil.py
checkvsphere/vcmd/__init__.py
checkvsphere/vcmd/about.py
checkvsphere/vcmd/datastores.py
checkvsphere/vcmd/hostnic.py
checkvsphere/vcmd/hostruntime.py
checkvsphere/vcmd/hostservice.py
checkvsphere/vcmd/hoststorage.py
checkvsphere/vcmd/listmetrics.py
checkvsphere/vcmd/media.py
checkvsphere/vcmd/perf.py
checkvsphere/vcmd/powerstate.py
checkvsphere/vcmd/snapshots.py
checkvsphere/vcmd/vmguestfs.py
checkvsphere/vcmd/vmnetdev.py
checkvsphere/vcmd/vmtools.py
checkvsphere/vcmd/vsan.py
checkvsphere-0.3.20.dist-info/entry_points.txt
checkvsphere-0.3.20.dist-info/licenses/LICENSE
checkvsphere-0.3.20.dist-info/licenses/LICENSE-VMWARE
checkvsphere-0.3.20.dist-info/WHEEL
checkvsphere-0.3.20.dist-info/METADATA
checkvsphere-0.3.20.dist-info/RECORD
