Metadata-Version: 2.4
Name: checkvsphere
Version: 0.3.20
Summary: check_vsphere monitoring plugin
Author-email: Danijel Tasov <danijel.tasov@consol.de>
Requires-Python: >= 3.6
Classifier: Development Status :: 3 - Alpha
Classifier: Topic :: System :: Monitoring
Classifier: License :: OSI Approved :: GNU Affero General Public License v3 or later (AGPLv3+)
License-File: LICENSE
License-File: LICENSE-VMWARE
Requires-Dist: pyvmomi >= 8.0.3.0.1, < 10
Requires-Dist: monplugin >= 0.6.1
Project-URL: documentation, https://consol.github.io/check_vsphere
Project-URL: homepage, https://github.com/consol/check_vsphere
Project-URL: issues, https://github.com/consol/check_vsphere/issues
Project-URL: repository, https://github.com/consol/check_vsphere.git
